jaredquicksamply.py
jaredquicksamply-0.0.1.dist-info/LICENSE
jaredquicksamply-0.0.1.dist-info/METADATA
jaredquicksamply-0.0.1.dist-info/WHEEL
jaredquicksamply-0.0.1.dist-info/top_level.txt
jaredquicksamply-0.0.1.dist-info/RECORD
