Metadata-Version: 2.1
Name: jaredquicksamply
Version: 0.0.1
Summary: jaredquicksamply Test Package for Demo
Home-page: UNKNOWN
Author: Jared Wilber
License: UNKNOWN
Platform: UNKNOWN
Classifier: Programming Language :: Python :: 3
Classifier: License :: OSI Approved :: MIT License
Classifier: Operating System :: OS Independent
Requires-Python: >=3.6
